pymportx/__init__.py
pymportx/auxiliary_functions.py
pymportx/kallisto.py
pymportx/rsem.py
pymportx/sailfish.py
pymportx/salmon.py
pymportx-0.2.0.dist-info/LICENSE.txt
pymportx-0.2.0.dist-info/METADATA
pymportx-0.2.0.dist-info/WHEEL
pymportx-0.2.0.dist-info/top_level.txt
pymportx-0.2.0.dist-info/RECORD
