Metadata-Version: 2.1
Name: pymportx
Version: 0.2.0
Summary: Pymportx is a Python package designed for fast gene count estimation using transcript quantification files generated by pseudoalignment or quasi-mapping tools. It is a Python adaptation of the widely-used Tximport R package from Bioconductor.
Home-page: https://github.com/victorsanchezarevalo/Pymportx
Author: Pena Gonzalez, P., Lozano-Paredes, D., Rojo, J. L., Bote-Curiel, L., & Sanchez-Arevalo Lobo, V. J.
Author-email: "Sanchez-Arevalo Lobo, V. J." <victor.sanchezarevalo@ufv.es>, " Bote-Curiel, L." <luis.bote@urjc.es>
Project-URL: Homepage, https://github.com/victorsanchezarevalo/Pymportx
Project-URL: Bug Tracker, https://github.com/victorsanchezarevalo/Pymportx/issues
Keywords: bioinformatics,gene expression,transcript quantification,pseudoalignment
Classifier: Programming Language :: Python :: 3
Classifier: License :: OSI Approved :: MIT License
Classifier: Operating System :: OS Independent
Requires-Python: >=3.6
License-File: LICENSE.txt
Requires-Dist: numpy>=1.18.0
Requires-Dist: pandas>=1.0.0
Requires-Dist: h5py>=3.1.0
Requires-Dist: anndata>=0.7.5
